mcp_wiki/__init__.py
mcp_wiki/__main__.py
mcp_wiki/server.py
mcp_wiki_nidhish-0.1.0.dist-info/METADATA
mcp_wiki_nidhish-0.1.0.dist-info/WHEEL
mcp_wiki_nidhish-0.1.0.dist-info/top_level.txt
mcp_wiki_nidhish-0.1.0.dist-info/RECORD
