Metadata-Version: 2.4
Name: mcp-wiki-nidhish
Version: 0.1.0
Summary: Add your description here
Requires-Python: >=3.13
Requires-Dist: beautifulsoup4>=4.13.4
Requires-Dist: html2text>=2025.4.15
Requires-Dist: mcp[cli]>=1.9.2
Requires-Dist: requests>=2.32.3
